.gitlab-ci.yml
.travis.yml
LICENSE
README.md
setup.cfg
setup.py
examples/bad.py
examples/bandit.py
examples/good.py
examples/logging-format.py
examples/order.py
examples/simplify.py
flake8_gl_codeclimate/__init__.py
flake8_gl_codeclimate.egg-info/PKG-INFO
flake8_gl_codeclimate.egg-info/SOURCES.txt
flake8_gl_codeclimate.egg-info/dependency_links.txt
flake8_gl_codeclimate.egg-info/entry_points.txt
flake8_gl_codeclimate.egg-info/requires.txt
flake8_gl_codeclimate.egg-info/top_level.txt
scripts/report-to-gl-codeclimate.py
tests/test_formatter.py
tests/test_integration.py